Github_Analyzer_StefanoMarano80017/Github_Analyzer_StefanoMarano80017/__init__.py
Github_Analyzer_StefanoMarano80017/Github_Analyzer_StefanoMarano80017/__main__.py
Github_Analyzer_StefanoMarano80017/Github_Analyzer_StefanoMarano80017/Datas/Broker.py
Github_Analyzer_StefanoMarano80017/Github_Analyzer_StefanoMarano80017/Datas/DAOS.py
Github_Analyzer_StefanoMarano80017/Github_Analyzer_StefanoMarano80017/Datas/DB_manager.py
Github_Analyzer_StefanoMarano80017/Github_Analyzer_StefanoMarano80017/Datas/QueryGit.py
Github_Analyzer_StefanoMarano80017/Github_Analyzer_StefanoMarano80017/Datas/Query_Txt.py
Github_Analyzer_StefanoMarano80017/Github_Analyzer_StefanoMarano80017/Datas/TokenUtil.py
Github_Analyzer_StefanoMarano80017/Github_Analyzer_StefanoMarano80017/Datas/__init__.py
Github_Analyzer_StefanoMarano80017/Github_Analyzer_StefanoMarano80017/GUI/Window_manager.py
Github_Analyzer_StefanoMarano80017/Github_Analyzer_StefanoMarano80017/GUI/__init__.py
Github_Analyzer_StefanoMarano80017/Github_Analyzer_StefanoMarano80017/Unit_elaborazione/Analisi_sorgente.py
Github_Analyzer_StefanoMarano80017/Github_Analyzer_StefanoMarano80017/Unit_elaborazione/Cloc_Analize.py
Github_Analyzer_StefanoMarano80017/Github_Analyzer_StefanoMarano80017/Unit_elaborazione/Controller.py
Github_Analyzer_StefanoMarano80017/Github_Analyzer_StefanoMarano80017/Unit_elaborazione/Request_Code.py
Github_Analyzer_StefanoMarano80017/Github_Analyzer_StefanoMarano80017/Unit_elaborazione/__init__.py
Github_Analyzer_StefanoMarano80017/Github_Analyzer_StefanoMarano80017/Util/__init__.py
Github_Analyzer_StefanoMarano80017/Github_Analyzer_StefanoMarano80017/Util/logger.py
github_analyzer-0.1.4.dist-info/METADATA
github_analyzer-0.1.4.dist-info/WHEEL
github_analyzer-0.1.4.dist-info/licenses/LICENSE
github_analyzer-0.1.4.dist-info/RECORD
