Metadata-Version: 2.1
Name: Github_analyzer
Version: 0.1.4
Summary: A Simple tool for analyze github repositories
Project-URL: Homepage, https://github.com/StefanoMarano80017/Github_analyzer
Project-URL: Bug Tracker, https://github.com/StefanoMarano80017/Github_analyzer/issues
Author-email: Stefano Marano <author@example.com>
Classifier: License :: OSI Approved :: MIT License
Classifier: Operating System :: OS Independent
Classifier: Programming Language :: Python :: 3
Requires-Python: >=3.10
